sanprofetta/__init__.py
sanprofetta/mobius.py
sanprofetta/nagase.py
sanprofetta/yellow.py
sansalvacion-0.0.4.dist-info/LICENSE
sansalvacion-0.0.4.dist-info/METADATA
sansalvacion-0.0.4.dist-info/WHEEL
sansalvacion-0.0.4.dist-info/top_level.txt
sansalvacion-0.0.4.dist-info/RECORD
