Metadata-Version: 2.1
Name: sansalvacion
Version: 0.0.4
Summary: ISAF invades San Salvacion, one of the first cities to be occupied when Erusia initiated its invasion.
Home-page: https://github.com/imhungryforpizza/sansalvacion
Author: Mobius 1
Author-email: squander@ixiom.net
Project-URL: Bug Tracker, https://github.com/imhungryforpizza/sansalvacion/issues
Classifier: Programming Language :: Python :: 3
Classifier: License :: OSI Approved :: MIT License
Classifier: Operating System :: OS Independent
Requires-Python: >=3.6
License-File: LICENSE
